issue_pub/__init__.py
issue_pub/cli.py
issue_pub/issue_api.py
issue_pub/issue_pub.py
issue_pub/main.py
issue_pub/todo_gen.py
issue_pub-0.1.3.dist-info/DESCRIPTION.rst
issue_pub-0.1.3.dist-info/METADATA
issue_pub-0.1.3.dist-info/RECORD
issue_pub-0.1.3.dist-info/WHEEL
issue_pub-0.1.3.dist-info/entry_points.txt
issue_pub-0.1.3.dist-info/metadata.json
issue_pub-0.1.3.dist-info/top_level.txt
