Metadata-Version: 2.0
Name: issue-pub
Version: 0.1.3
Summary: git lab issue pub program
Home-page: https://github.com/wangshub/issue_pub
Author: easternslope
Author-email: easternslope@yeah.net
License: MIT license
Keywords: issue_pub
Platform: UNKNOWN
Classifier: Development Status :: 2 - Pre-Alpha
Classifier: Intended Audience :: Developers
Classifier: License :: OSI Approved :: MIT License
Classifier: Natural Language :: English
Classifier: Programming Language :: Python :: 2
Classifier: Programming Language :: Python :: 2.6
Classifier: Programming Language :: Python :: 2.7
Classifier: Programming Language :: Python :: 3
Classifier: Programming Language :: Python :: 3.3
Classifier: Programming Language :: Python :: 3.4
Classifier: Programming Language :: Python :: 3.5
Requires-Dist: Click (>=6.0)
